cesail/__init__.py
cesail/cesail_mcp/README.md
cesail/cesail_mcp/__init__.py
cesail/cesail_mcp/fastmcp_server.py
cesail/cesail_mcp/tests/test_mcp_server.py
cesail/cesail_mcp/tests/test_mcp_server_simple.py
cesail/dom_parser/README.md
cesail/dom_parser/__init__.py
cesail/dom_parser/package-lock.json
cesail/dom_parser/package.json
cesail/dom_parser/rollup.config.js
cesail/dom_parser/setup.py
cesail/dom_parser/dist/dom-parser.js
cesail/dom_parser/node_modules/.package-lock.json
cesail/dom_parser/node_modules/.bin/resolve
cesail/dom_parser/node_modules/@rollup/plugin-node-resolve/LICENSE
cesail/dom_parser/node_modules/@rollup/plugin-node-resolve/README.md
cesail/dom_parser/node_modules/@rollup/plugin-node-resolve/package.json
cesail/dom_parser/node_modules/@rollup/plugin-node-resolve/dist/cjs/index.js
cesail/dom_parser/node_modules/@rollup/plugin-node-resolve/dist/es/index.js
cesail/dom_parser/node_modules/@rollup/plugin-node-resolve/dist/es/package.json
cesail/dom_parser/node_modules/@rollup/plugin-node-resolve/types/index.d.ts
cesail/dom_parser/node_modules/@rollup/pluginutils/LICENSE
cesail/dom_parser/node_modules/@rollup/pluginutils/README.md
cesail/dom_parser/node_modules/@rollup/pluginutils/package.json
cesail/dom_parser/node_modules/@rollup/pluginutils/dist/cjs/index.js
cesail/dom_parser/node_modules/@rollup/pluginutils/dist/es/index.js
cesail/dom_parser/node_modules/@rollup/pluginutils/dist/es/package.json
cesail/dom_parser/node_modules/@rollup/pluginutils/types/index.d.ts
cesail/dom_parser/node_modules/@types/estree/LICENSE
cesail/dom_parser/node_modules/@types/estree/README.md
cesail/dom_parser/node_modules/@types/estree/flow.d.ts
cesail/dom_parser/node_modules/@types/estree/index.d.ts
cesail/dom_parser/node_modules/@types/estree/package.json
cesail/dom_parser/node_modules/@types/resolve/LICENSE
cesail/dom_parser/node_modules/@types/resolve/README.md
cesail/dom_parser/node_modules/@types/resolve/index.d.ts
cesail-0.2.3.dist-info/licenses/LICENSE
cesail-0.2.3.dist-info/METADATA
cesail-0.2.3.dist-info/WHEEL
cesail-0.2.3.dist-info/top_level.txt
cesail-0.2.3.dist-info/RECORD
