Metadata-Version: 2.4
Name: cesail
Version: 0.2.3
Summary: A comprehensive web automation and DOM parsing platform with AI-powered agents
Home-page: https://github.com/AkilaJay/cesail
Author: Rachita Pradeep
Author-email: Akila Jayawardane <ajjayawardane@gmail.com>
Maintainer-email: Akila Jayawardane <ajjayawardane@gmail.com>
License: MIT
Project-URL: Homepage, https://github.com/AkilaJay/CeSail
Project-URL: Documentation, https://github.com/AkilaJay/CeSail#readme
Project-URL: Repository, https://github.com/AkilaJay/CeSail
Project-URL: Issues, https://github.com/AkilaJay/CeSail/issues
Project-URL: Changelog, https://github.com/AkilaJay/CeSail/blob/main/CHANGELOG.md
Keywords: web-automation,dom-parser,ai,playwright,mcp,web-scraping
Classifier: Development Status :: 3 - Alpha
Classifier: Intended Audience :: Developers
Classifier: License :: OSI Approved :: MIT License
Classifier: Programming Language :: Python :: 3
Classifier: Programming Language :: Python :: 3.9
Classifier: Programming Language :: Python :: 3.10
Classifier: Programming Language :: Python :: 3.11
Classifier: Programming Language :: Python :: 3.12
Classifier: Topic :: Software Development :: Libraries :: Python Modules
Classifier: Topic :: Internet :: WWW/HTTP :: Browsers
Classifier: Topic :: Scientific/Engineering :: Artificial Intelligence
Requires-Python: >=3.9
License-File: LICENSE
Requires-Dist: playwright>=1.40.0
Requires-Dist: pytest>=8.0.0
Requires-Dist: pytest-asyncio>=0.23.0
Requires-Dist: pydantic>=2.0.0
Requires-Dist: fastmcp<3.0.0,>=2.0.0
Requires-Dist: mcp<1.13.0,>=1.12.4
Requires-Dist: openai>=1.0.0
Requires-Dist: anthropic>=0.64.0
Requires-Dist: tenacity>=8.0.0
Requires-Dist: python-dotenv>=1.0.0
Provides-Extra: dev
Requires-Dist: pytest>=8.0.0; extra == "dev"
Requires-Dist: pytest-asyncio>=0.23.0; extra == "dev"
Requires-Dist: black>=22.0.0; extra == "dev"
Requires-Dist: isort>=5.0.0; extra == "dev"
Requires-Dist: mypy>=1.0.0; extra == "dev"
Requires-Dist: flake8>=4.0.0; extra == "dev"
Provides-Extra: docs
Requires-Dist: sphinx>=4.0.0; extra == "docs"
Requires-Dist: sphinx-rtd-theme>=1.0.0; extra == "docs"
Dynamic: author
Dynamic: home-page
Dynamic: license-file
Dynamic: requires-python
